totpy
